tcsstamp/__init__.py
tcsstamp/__main__.py
tcsstamp/__version__.py
tcsstamp/console.py
tcsstamp/echo_server.py
tcsstamp/process.py
tcsstamp/sock_if.py
tcsstamp/tcs_stamp_converter.py
tcs_stamp_converter-0.3.7.dist-info/LICENSE
tcs_stamp_converter-0.3.7.dist-info/METADATA
tcs_stamp_converter-0.3.7.dist-info/WHEEL
tcs_stamp_converter-0.3.7.dist-info/entry_points.txt
tcs_stamp_converter-0.3.7.dist-info/top_level.txt
tcs_stamp_converter-0.3.7.dist-info/RECORD
