Metadata-Version: 2.1
Name: tcs-stamp-converter
Version: 0.3.7
Summary: Convert the telemetry stream from the TCS EGSE into a STAMP compatible interface.
Home-page: https://github.com/rhuygen/tcsstamp
Author: Rik Huygen
Author-email: rik.huygen@kuleuven.be
License: MIT
Platform: UNKNOWN
Classifier: License :: OSI Approved :: MIT License
Classifier: Environment :: Console
Classifier: Programming Language :: Python :: 3
Classifier: Programming Language :: Python :: 3.8
Requires-Python: >=3.8.0
Provides-Extra: fancy_output
Requires-Dist: rich ; extra == 'fancy_output'
